zombus/__init__.py
zombus/py.typed
zombus/definitions/__init__.py
zombus/definitions/contracts.py
zombus/definitions/enums.py
zombus/definitions/errors.py
zombus/patterns/__init__.py
zombus/patterns/errors/__init__.py
zombus/patterns/errors/data.py
zombus/patterns/errors/generic.py
zombus/patterns/messages/__init__.py
zombus/patterns/messages/generic.py
zombus/patterns/messages/views.py
zombus/processing/__init__.py
zombus/processing/enums.py
zombus/processing/internals.py
zombus/processing/pipeline.py
zombus/processing/processors.py
zombus/registration/__init__.py
zombus/registration/collecting.py
zombus/registration/entities.py
zombus/registration/registry.py
zombus-0.3.1.dist-info/METADATA
zombus-0.3.1.dist-info/WHEEL
zombus-0.3.1.dist-info/RECORD
